coinrailz_mcp/__init__.py
coinrailz_mcp/__main__.py
coinrailz_mcp-1.0.5.dist-info/METADATA
coinrailz_mcp-1.0.5.dist-info/WHEEL
coinrailz_mcp-1.0.5.dist-info/entry_points.txt
coinrailz_mcp-1.0.5.dist-info/licenses/LICENSE
coinrailz_mcp-1.0.5.dist-info/RECORD
