Metadata-Version: 2.4
Name: coinrailz-mcp
Version: 1.0.5
Summary: MCP server exposing 41 Coin Railz x402 micropayment crypto services to Claude including stock & forex sentiment
Project-URL: Homepage, https://coinrailz.com
Project-URL: Documentation, https://coinrailz.com/developers
Project-URL: Repository, https://github.com/coinrailz/mcp-server-coinrailz
Project-URL: Issues, https://github.com/coinrailz/mcp-server-coinrailz/issues
Project-URL: Changelog, https://github.com/coinrailz/mcp-server-coinrailz/releases
Author-email: Coin Railz <support@coinrailz.com>
License: MIT
License-File: LICENSE
Keywords: anthropic,base,blockchain,claude,crypto,defi,ethereum,mcp,payments,trading,usdc,x402
Classifier: Development Status :: 4 - Beta
Classifier: Intended Audience :: Developers
Classifier: License :: OSI Approved :: MIT License
Classifier: Programming Language :: Python :: 3.10
Classifier: Programming Language :: Python :: 3.11
Classifier: Programming Language :: Python :: 3.12
Classifier: Topic :: Internet :: WWW/HTTP
Classifier: Topic :: Office/Business :: Financial
Classifier: Topic :: Software Development :: Libraries
Requires-Python: >=3.10
Requires-Dist: httpx>=0.25.0
Requires-Dist: mcp>=1.0.0
